instrmcp/__init__.py
instrmcp/cli.py
instrmcp/setup_utils.py
instrmcp/config/__init__.py
instrmcp/config/data/default_station.yaml
instrmcp/extensions/__init__.py
instrmcp/extensions/MeasureIt/__init__.py
instrmcp/extensions/MeasureIt/measureit_templates.py
instrmcp/extensions/database/__init__.py
instrmcp/extensions/database/db_resources.py
instrmcp/extensions/database/query_tools.py
instrmcp/extensions/jupyterlab/.yarnrc.yml
instrmcp/extensions/jupyterlab/README.md
instrmcp/extensions/jupyterlab/__init__.py
instrmcp/extensions/jupyterlab/install.json
instrmcp/extensions/jupyterlab/package.json
instrmcp/extensions/jupyterlab/setup.py
instrmcp/extensions/jupyterlab/tsconfig.json
instrmcp/extensions/jupyterlab/mcp_active_cell_bridge/__init__.py
instrmcp/extensions/jupyterlab/mcp_active_cell_bridge/labextension/package.json
instrmcp/extensions/jupyterlab/mcp_active_cell_bridge/labextension/static/481.3109a72fae77efe39818.js
instrmcp/extensions/jupyterlab/mcp_active_cell_bridge/labextension/static/509.e64debb6dfa67297cbc0.js
instrmcp/extensions/jupyterlab/mcp_active_cell_bridge/labextension/static/665.4a5730eea9261e54b920.js
instrmcp/extensions/jupyterlab/mcp_active_cell_bridge/labextension/static/remoteEntry.f3baf0d7bab1abfa32d3.js
instrmcp/extensions/jupyterlab/mcp_active_cell_bridge/labextension/static/style.js
instrmcp/extensions/jupyterlab/mcp_active_cell_bridge/labextension/static/third-party-licenses.json
instrmcp/extensions/jupyterlab/static/package.json
instrmcp/extensions/jupyterlab/static/static/third-party-licenses.json
instrmcp/servers/__init__.py
instrmcp/servers/jupyter_qcodes/__init__.py
instrmcp/servers/jupyter_qcodes/active_cell_bridge.py
instrmcp/servers/jupyter_qcodes/cache.py
instrmcp/servers/jupyter_qcodes/dynamic_registrar.py
instrmcp/servers/jupyter_qcodes/dynamic_runtime.py
instrmcp/servers/jupyter_qcodes/jupyter_mcp_extension.py
instrmcp/servers/jupyter_qcodes/mcp_server.py
instrmcp/servers/jupyter_qcodes/run_standalone.py
instrmcp-2.0.1.dist-info/licenses/LICENSE
instrmcp-2.0.1.dist-info/METADATA
instrmcp-2.0.1.dist-info/WHEEL
instrmcp-2.0.1.dist-info/entry_points.txt
instrmcp-2.0.1.dist-info/top_level.txt
instrmcp-2.0.1.dist-info/RECORD
