Metadata-Version: 2.4
Name: instrmcp
Version: 2.0.1
Summary: MCP server suite for physics laboratory instrumentation control
Author-email: Jiaqi Cai <jiaqic@mit.edu>
Maintainer-email: Jiaqi Cai <jiaqic@mit.edu>
License: MIT License
Project-URL: Homepage, https://github.com/instrmcp/instrMCP
Project-URL: Documentation, https://instrmcp.readthedocs.io
Project-URL: Repository, https://github.com/instrmcp/instrMCP.git
Project-URL: Issues, https://github.com/instrmcp/instrMCP/issues
Project-URL: Changelog, https://github.com/instrmcp/instrMCP/blob/main/CHANGELOG.md
Keywords: mcp,model-context-protocol,qcodes,instrumentation,physics,laboratory,measurement,automation
Classifier: Development Status :: 4 - Beta
Classifier: Intended Audience :: Science/Research
Classifier: Topic :: Scientific/Engineering :: Physics
Classifier: Topic :: System :: Hardware
Classifier: License :: OSI Approved :: MIT License
Classifier: Framework :: Jupyter :: JupyterLab :: Extensions :: Prebuilt
Classifier: Programming Language :: Python :: 3
Classifier: Programming Language :: Python :: 3.10
Classifier: Programming Language :: Python :: 3.11
Classifier: Programming Language :: Python :: 3.12
Requires-Python: >=3.10
License-File: LICENSE
Requires-Dist: fastmcp>=0.1.0
Requires-Dist: mcp>=1.0.0
Requires-Dist: pyyaml>=6.0
Requires-Dist: httpx>=0.25.0
Requires-Dist: qcodes>=0.45.0
Requires-Dist: numpy>=1.24.0
Requires-Dist: pandas>=2.0.0
Requires-Dist: matplotlib>=3.7.0
Requires-Dist: scipy>=1.10.0
Requires-Dist: h5py>=3.8.0
Requires-Dist: xarray>=2023.1.0
Requires-Dist: jupyterlab<5,>=4.0.0
Requires-Dist: ipython>=8.0.0
Requires-Dist: notebook>=6.4.0
Requires-Dist: jupyter-core>=5.0.0
Provides-Extra: jupyter
Provides-Extra: qcodes
Provides-Extra: redpitaya
Requires-Dist: pyrpl>=0.9.4; extra == "redpitaya"
Requires-Dist: scipy>=1.10.0; extra == "redpitaya"
Requires-Dist: numpy>=1.24.0; extra == "redpitaya"
Provides-Extra: dev
Requires-Dist: pytest>=7.0.0; extra == "dev"
Requires-Dist: pytest-asyncio>=0.21.0; extra == "dev"
Requires-Dist: pytest-cov>=4.0.0; extra == "dev"
Requires-Dist: black>=23.0.0; extra == "dev"
Requires-Dist: flake8>=6.0.0; extra == "dev"
Requires-Dist: mypy>=1.0.0; extra == "dev"
Requires-Dist: pre-commit>=3.0.0; extra == "dev"
Provides-Extra: docs
Requires-Dist: sphinx>=6.0.0; extra == "docs"
Requires-Dist: sphinx-rtd-theme>=1.3.0; extra == "docs"
Requires-Dist: sphinx-autodoc-typehints>=1.19.0; extra == "docs"
Provides-Extra: full
Requires-Dist: instrmcp[jupyter,qcodes]; extra == "full"
Dynamic: license-file
